nna_methods/__init__.py
nna_methods-0.6.0.dist-info/LICENSE
nna_methods-0.6.0.dist-info/METADATA
nna_methods-0.6.0.dist-info/WHEEL
nna_methods-0.6.0.dist-info/top_level.txt
nna_methods-0.6.0.dist-info/RECORD
