Metadata-Version: 2.1
Name: nna-methods
Version: 0.6.0
Summary: Nearest Neighbor Averaging methods
Author: Barron H. Henderson
Author-email: barronh@gmail.com
License-File: LICENSE
Requires-Dist: numpy
Requires-Dist: scipy
Requires-Dist: pandas
Requires-Dist: scikit-learn
